{
  "messageType": "UpdateLeaderboardData",
  "payload": {
    "message": {
      "region": "",
      "gameMode": "1v1",
      "race": "all",
      "seasonId": 4,
      "totalrows": 7625,
      "totalpages": 305,
      "currentpage": 156,
      "hasError": false,
      "errorMessage": "",
      "rows": [
        {
          "race": "undead",
          "players": [
            {
              "toonName": "RegularGamer",
              "battleTag": "RegularGamer#21581",
              "avatarId": "p092",
              "accountCreationTime": 18446744073253881739
            }
          ],
          "region": "",
          "mmr": 4820,
          "gameMode": "",
          "rank": 3876,
          "wins": 3,
          "losses": 4,
          "draws": 0,
          "division": 3
        },
        {
          "race": "orc",
          "players": [
            {
              "toonName": "SecretDream",
              "battleTag": "SecretDream#11630",
              "avatarId": "",
              "accountCreationTime": 18446744072127407566
            }
          ],
          "region": "",
          "mmr": 4819,
          "gameMode": "",
          "rank": 3877,
          "wins": 52,
          "losses": 51,
          "draws": 0,
          "division": 3
        },
        {
          "race": "undead",
          "players": [
            {
              "toonName": "Rainleung",
              "battleTag": "Rainleung#31339",
              "avatarId": "",
              "accountCreationTime": 18446744071648429660
            }
          ],
          "region": "",
          "mmr": 4819,
          "gameMode": "",
          "rank": 3878,
          "wins": 3,
          "losses": 4,
          "draws": 0,
          "division": 3
        },
        {
          "race": "night_elf",
          "players": [
            {
              "toonName": "mo2l",
              "battleTag": "mo2l#2314",
              "avatarId": "p049",
              "accountCreationTime": 18446744073509329732
            }
          ],
          "region": "",
          "mmr": 4819,
          "gameMode": "",
          "rank": 3879,
          "wins": 4,
          "losses": 6,
          "draws": 0,
          "division": 3
        },
        {
          "race": "undead",
          "players": [
            {
              "toonName": "천년의사랑",
              "battleTag": "천년의사랑#31973",
              "avatarId": "",
              "accountCreationTime": 1146708883
            }
          ],
          "region": "",
          "mmr": 4819,
          "gameMode": "",
          "rank": 3880,
          "wins": 2,
          "losses": 3,
          "draws": 0,
          "division": 3
        },
        {
          "race": "night_elf",
          "players": [
            {
              "toonName": "omni",
              "battleTag": "omni#21311",
              "avatarId": "p077",
              "accountCreationTime": 349030038
            }
          ],
          "region": "",
          "mmr": 4819,
          "gameMode": "",
          "rank": 3881,
          "wins": 5,
          "losses": 5,
          "draws": 0,
          "division": 3
        },
        {
          "race": "human",
          "players": [
            {
              "toonName": "Mikasa",
              "battleTag": "Mikasa#2390",
              "avatarId": "p086",
              "accountCreationTime": 1170826415
            }
          ],
          "region": "",
          "mmr": 4819,
          "gameMode": "",
          "rank": 3882,
          "wins": 8,
          "losses": 5,
          "draws": 0,
          "division": 3
        },
        {
          "race": "undead",
          "players": [
            {
              "toonName": "candybober",
              "battleTag": "candybober#21218",
              "avatarId": "",
              "accountCreationTime": 18446744072837686924
            }
          ],
          "region": "",
          "mmr": 4818,
          "gameMode": "",
          "rank": 3883,
          "wins": 2,
          "losses": 4,
          "draws": 0,
          "division": 3
        },
        {
          "race": "human",
          "players": [
            {
              "toonName": "古仔",
              "battleTag": "古仔#31422",
              "avatarId": "",
              "accountCreationTime": 18446744073498740169
            }
          ],
          "region": "",
          "mmr": 4818,
          "gameMode": "",
          "rank": 3884,
          "wins": 3,
          "losses": 5,
          "draws": 0,
          "division": 3
        },
        {
          "race": "human",
          "players": [
            {
              "toonName": "GYAPA",
              "battleTag": "GYAPA#2928",
              "avatarId": "p094",
              "accountCreationTime": 429025446
            }
          ],
          "region": "",
          "mmr": 4818,
          "gameMode": "",
          "rank": 3885,
          "wins": 6,
          "losses": 5,
          "draws": 0,
          "division": 3
        },
        {
          "race": "orc",
          "players": [
            {
              "toonName": "OrangeLight",
              "battleTag": "OrangeLight#1770",
              "avatarId": "",
              "accountCreationTime": 1266811743
            }
          ],
          "region": "",
          "mmr": 4818,
          "gameMode": "",
          "rank": 3886,
          "wins": 25,
          "losses": 25,
          "draws": 0,
          "division": 3
        },
        {
          "race": "human",
          "players": [
            {
              "toonName": "Williamyoung",
              "battleTag": "Williamyoung#1315",
              "avatarId": "",
              "accountCreationTime": 18446744072838000915
            }
          ],
          "region": "",
          "mmr": 4818,
          "gameMode": "",
          "rank": 3887,
          "wins": 13,
          "losses": 16,
          "draws": 0,
          "division": 3
        },
        {
          "race": "human",
          "players": [
            {
              "toonName": "Rocket123",
              "battleTag": "Rocket123#21586",
              "avatarId": "p046",
              "accountCreationTime": 18446744072692365356
            }
          ],
          "region": "",
          "mmr": 4818,
          "gameMode": "",
          "rank": 3888,
          "wins": 3,
          "losses": 3,
          "draws": 0,
          "division": 3
        },
        {
          "race": "human",
          "players": [
            {
              "toonName": "IuriVasques",
              "battleTag": "IuriVasques#1108",
              "avatarId": "p045",
              "accountCreationTime": 18446744073057079140
            }
          ],
          "region": "",
          "mmr": 4818,
          "gameMode": "",
          "rank": 3889,
          "wins": 12,
          "losses": 11,
          "draws": 0,
          "division": 3
        },
        {
          "race": "orc",
          "players": [
            {
              "toonName": "Outlaw",
              "battleTag": "Outlaw#31790",
              "avatarId": "",
              "accountCreationTime": 18446744073478249039
            }
          ],
          "region": "",
          "mmr": 4818,
          "gameMode": "",
          "rank": 3890,
          "wins": 4,
          "losses": 5,
          "draws": 0,
          "division": 3
        },
        {
          "race": "undead",
          "players": [
            {
              "toonName": "BlackPesca",
              "battleTag": "BlackPesca#2412",
              "avatarId": "p001",
              "accountCreationTime": 1036454281
            }
          ],
          "region": "",
          "mmr": 4818,
          "gameMode": "",
          "rank": 3891,
          "wins": 13,
          "losses": 13,
          "draws": 0,
          "division": 3
        },
        {
          "race": "undead",
          "players": [
            {
              "toonName": "verywindy",
              "battleTag": "verywindy#2541",
              "avatarId": "p050",
              "accountCreationTime": 18446744072554146249
            }
          ],
          "region": "",
          "mmr": 4817,
          "gameMode": "",
          "rank": 3892,
          "wins": 3,
          "losses": 4,
          "draws": 0,
          "division": 3
        },
        {
          "race": "undead",
          "players": [
            {
              "toonName": "dndark",
              "battleTag": "dndark#1916",
              "avatarId": "",
              "accountCreationTime": 18446744072695293730
            }
          ],
          "region": "",
          "mmr": 4817,
          "gameMode": "",
          "rank": 3893,
          "wins": 6,
          "losses": 5,
          "draws": 0,
          "division": 3
        },
        {
          "race": "random",
          "players": [
            {
              "toonName": "GoblinZeh",
              "battleTag": "GoblinZeh#2778",
              "avatarId": "p069",
              "accountCreationTime": 18446744072797001314
            }
          ],
          "region": "",
          "mmr": 4817,
          "gameMode": "",
          "rank": 3894,
          "wins": 3,
          "losses": 3,
          "draws": 0,
          "division": 3
        },
        {
          "race": "random",
          "players": [
            {
              "toonName": "Mebius",
              "battleTag": "Mebius#3306",
              "avatarId": "",
              "accountCreationTime": 809904713
            }
          ],
          "region": "",
          "mmr": 4817,
          "gameMode": "",
          "rank": 3895,
          "wins": 49,
          "losses": 46,
          "draws": 0,
          "division": 3
        },
        {
          "race": "human",
          "players": [
            {
              "toonName": "zzbyna",
              "battleTag": "zzbyna#2213",
              "avatarId": "",
              "accountCreationTime": 483954937
            }
          ],
          "region": "",
          "mmr": 4817,
          "gameMode": "",
          "rank": 3896,
          "wins": 10,
          "losses": 11,
          "draws": 0,
          "division": 3
        },
        {
          "race": "human",
          "players": [
            {
              "toonName": "Qenthalaz",
              "battleTag": "Qenthalaz#1871",
              "avatarId": "",
              "accountCreationTime": 2077226618
            }
          ],
          "region": "",
          "mmr": 4817,
          "gameMode": "",
          "rank": 3897,
          "wins": 6,
          "losses": 6,
          "draws": 0,
          "division": 3
        },
        {
          "race": "human",
          "players": [
            {
              "toonName": "Martin171142",
              "battleTag": "Martin171142#2965",
              "avatarId": "p096",
              "accountCreationTime": 18446744073630051947
            }
          ],
          "region": "",
          "mmr": 4817,
          "gameMode": "",
          "rank": 3898,
          "wins": 57,
          "losses": 54,
          "draws": 0,
          "division": 3
        },
        {
          "race": "orc",
          "players": [
            {
              "toonName": "KyoOblitZ",
              "battleTag": "KyoOblitZ#1594",
              "avatarId": "",
              "accountCreationTime": 1785516979
            }
          ],
          "region": "",
          "mmr": 4816,
          "gameMode": "",
          "rank": 3899,
          "wins": 8,
          "losses": 6,
          "draws": 0,
          "division": 3
        },
        {
          "race": "night_elf",
          "players": [
            {
              "toonName": "Wisper",
              "battleTag": "Wisper#31521",
              "avatarId": "",
              "accountCreationTime": 18446744072905539627
            }
          ],
          "region": "",
          "mmr": 4816,
          "gameMode": "",
          "rank": 3900,
          "wins": 20,
          "losses": 20,
          "draws": 0,
          "division": 3
        }
      ],
      "lastAccessTime": 1707079282
    }
  }
}