{
  "messageType": "UpdateLeaderboardData",
  "payload": {
    "message": {
      "region": "",
      "gameMode": "1v1",
      "race": "all",
      "seasonId": 3,
      "totalrows": 42950,
      "totalpages": 1718,
      "currentpage": 1261,
      "hasError": false,
      "errorMessage": "",
      "rows": [
        {
          "race": "undead",
          "players": [
            {
              "toonName": "ThreeWitches",
              "battleTag": "ThreeWitches#1598",
              "avatarId": "",
              "accountCreationTime": 18446744072602814576
            }
          ],
          "region": "",
          "mmr": 4157,
          "gameMode": "",
          "rank": 31501,
          "wins": 0,
          "losses": 6,
          "draws": 0,
          "division": 3
        },
        {
          "race": "undead",
          "players": [
            {
              "toonName": "Pepper",
              "battleTag": "Pepper#12941",
              "avatarId": "",
              "accountCreationTime": 1935576189
            }
          ],
          "region": "",
          "mmr": 4157,
          "gameMode": "",
          "rank": 31502,
          "wins": 222,
          "losses": 189,
          "draws": 0,
          "division": 3
        },
        {
          "race": "orc",
          "players": [
            {
              "toonName": "Gandalf",
              "battleTag": "Gandalf#22589",
              "avatarId": "p004",
              "accountCreationTime": 1927593668
            }
          ],
          "region": "",
          "mmr": 4157,
          "gameMode": "",
          "rank": 31503,
          "wins": 5,
          "losses": 11,
          "draws": 0,
          "division": 3
        },
        {
          "race": "human",
          "players": [
            {
              "toonName": "bliss",
              "battleTag": "bliss#31346",
              "avatarId": "",
              "accountCreationTime": 2123162619
            }
          ],
          "region": "",
          "mmr": 4157,
          "gameMode": "",
          "rank": 31504,
          "wins": 556,
          "losses": 516,
          "draws": 0,
          "division": 3
        },
        {
          "race": "undead",
          "players": [
            {
              "toonName": "Torkan",
              "battleTag": "Torkan#2443",
              "avatarId": ""
            }
          ],
          "region": "",
          "mmr": 4157,
          "gameMode": "",
          "rank": 31505,
          "wins": 10,
          "losses": 13,
          "draws": 0,
          "division": 3
        },
        {
          "race": "orc",
          "players": [
            {
              "toonName": "Gwynbleidd",
              "battleTag": "Gwynbleidd#22162",
              "avatarId": "p109",
              "accountCreationTime": 19441930
            }
          ],
          "region": "",
          "mmr": 4157,
          "gameMode": "",
          "rank": 31506,
          "wins": 671,
          "losses": 635,
          "draws": 0,
          "division": 3
        },
        {
          "race": "human",
          "players": [
            {
              "toonName": "시비사천왕",
              "battleTag": "시비사천왕#3820",
              "avatarId": "",
              "accountCreationTime": 826166039
            }
          ],
          "region": "",
          "mmr": 4157,
          "gameMode": "",
          "rank": 31507,
          "wins": 0,
          "losses": 7,
          "draws": 0,
          "division": 3
        },
        {
          "race": "random",
          "players": [
            {
              "toonName": "FromChaos117",
              "battleTag": "FromChaos117#1433",
              "avatarId": "",
              "accountCreationTime": 37105081
            }
          ],
          "region": "",
          "mmr": 4157,
          "gameMode": "",
          "rank": 31508,
          "wins": 69,
          "losses": 83,
          "draws": 0,
          "division": 3
        },
        {
          "race": "human",
          "players": [
            {
              "toonName": "Casablanka",
              "battleTag": "Casablanka#2792",
              "avatarId": "p007",
              "accountCreationTime": 18446744072233814110
            }
          ],
          "region": "",
          "mmr": 4157,
          "gameMode": "",
          "rank": 31509,
          "wins": 0,
          "losses": 7,
          "draws": 0,
          "division": 3
        },
        {
          "race": "random",
          "players": [
            {
              "toonName": "haha",
              "battleTag": "haha#21962",
              "avatarId": "p086",
              "accountCreationTime": 755100038
            }
          ],
          "region": "",
          "mmr": 4156,
          "gameMode": "",
          "rank": 31510,
          "wins": 0,
          "losses": 6,
          "draws": 0,
          "division": 3
        },
        {
          "race": "orc",
          "players": [
            {
              "toonName": "BulldoggeMom",
              "battleTag": "BulldoggeMom#1693",
              "avatarId": "",
              "accountCreationTime": 1823843819
            }
          ],
          "region": "",
          "mmr": 4156,
          "gameMode": "",
          "rank": 31511,
          "wins": 0,
          "losses": 6,
          "draws": 0,
          "division": 3
        },
        {
          "race": "orc",
          "players": [
            {
              "toonName": "BonzO",
              "battleTag": "BonzO#21122",
              "avatarId": "p035",
              "accountCreationTime": 325399553
            }
          ],
          "region": "",
          "mmr": 4156,
          "gameMode": "",
          "rank": 31512,
          "wins": 17,
          "losses": 19,
          "draws": 0,
          "division": 3
        },
        {
          "race": "orc",
          "players": [
            {
              "toonName": "Nygold15",
              "battleTag": "Nygold15#1352",
              "avatarId": "",
              "accountCreationTime": 440978164
            }
          ],
          "region": "",
          "mmr": 4156,
          "gameMode": "",
          "rank": 31513,
          "wins": 0,
          "losses": 6,
          "draws": 0,
          "division": 3
        },
        {
          "race": "undead",
          "players": [
            {
              "toonName": "sham",
              "battleTag": "sham#21878",
              "avatarId": "p041",
              "accountCreationTime": 18446744072608419610
            }
          ],
          "region": "",
          "mmr": 4156,
          "gameMode": "",
          "rank": 31514,
          "wins": 135,
          "losses": 126,
          "draws": 0,
          "division": 3
        },
        {
          "race": "human",
          "players": [
            {
              "toonName": "卑劣的紅色鶴",
              "battleTag": "卑劣的紅色鶴#31299",
              "avatarId": "",
              "accountCreationTime": 307473879
            }
          ],
          "region": "",
          "mmr": 4156,
          "gameMode": "",
          "rank": 31515,
          "wins": 13,
          "losses": 23,
          "draws": 0,
          "division": 3
        },
        {
          "race": "human",
          "players": [
            {
              "toonName": "mandy",
              "battleTag": "mandy#11736",
              "avatarId": "",
              "accountCreationTime": 18446744072570766204
            }
          ],
          "region": "",
          "mmr": 4156,
          "gameMode": "",
          "rank": 31516,
          "wins": 5,
          "losses": 12,
          "draws": 0,
          "division": 3
        },
        {
          "race": "human",
          "players": [
            {
              "toonName": "whosyourdad",
              "battleTag": "whosyourdad#11286",
              "avatarId": "",
              "accountCreationTime": 1092113692
            }
          ],
          "region": "",
          "mmr": 4156,
          "gameMode": "",
          "rank": 31517,
          "wins": 4,
          "losses": 12,
          "draws": 0,
          "division": 3
        },
        {
          "race": "human",
          "players": [
            {
              "toonName": "Edan",
              "battleTag": "Edan#2818",
              "avatarId": "p033",
              "accountCreationTime": 1960365295
            }
          ],
          "region": "",
          "mmr": 4156,
          "gameMode": "",
          "rank": 31518,
          "wins": 2,
          "losses": 6,
          "draws": 0,
          "division": 3
        },
        {
          "race": "orc",
          "players": [
            {
              "toonName": "애송이",
              "battleTag": "애송이#31525",
              "avatarId": "",
              "accountCreationTime": 1780947747
            }
          ],
          "region": "",
          "mmr": 4156,
          "gameMode": "",
          "rank": 31519,
          "wins": 594,
          "losses": 610,
          "draws": 0,
          "division": 3
        },
        {
          "race": "orc",
          "players": [
            {
              "toonName": "Fipped",
              "battleTag": "Fipped#1709",
              "avatarId": "",
              "accountCreationTime": 1123291768
            }
          ],
          "region": "",
          "mmr": 4156,
          "gameMode": "",
          "rank": 31520,
          "wins": 2,
          "losses": 10,
          "draws": 0,
          "division": 3
        },
        {
          "race": "undead",
          "players": [
            {
              "toonName": "yumikocjw",
              "battleTag": "yumikocjw#3315",
              "avatarId": "p001",
              "accountCreationTime": 1999575096
            }
          ],
          "region": "",
          "mmr": 4156,
          "gameMode": "",
          "rank": 31521,
          "wins": 372,
          "losses": 380,
          "draws": 0,
          "division": 3
        },
        {
          "race": "human",
          "players": [
            {
              "toonName": "twoshoe",
              "battleTag": "twoshoe#11777",
              "avatarId": "",
              "accountCreationTime": 18446744073053432107
            }
          ],
          "region": "",
          "mmr": 4156,
          "gameMode": "",
          "rank": 31522,
          "wins": 101,
          "losses": 106,
          "draws": 0,
          "division": 3
        },
        {
          "race": "human",
          "players": [
            {
              "toonName": "euroser",
              "battleTag": "euroser#2693",
              "avatarId": "p033",
              "accountCreationTime": 18446744073292414959
            }
          ],
          "region": "",
          "mmr": 4156,
          "gameMode": "",
          "rank": 31523,
          "wins": 50,
          "losses": 62,
          "draws": 0,
          "division": 3
        },
        {
          "race": "orc",
          "players": [
            {
              "toonName": "CallMeKeeper",
              "battleTag": "CallMeKeeper#2170",
              "avatarId": "",
              "accountCreationTime": 18446744072347663112
            }
          ],
          "region": "",
          "mmr": 4156,
          "gameMode": "",
          "rank": 31524,
          "wins": 7,
          "losses": 16,
          "draws": 0,
          "division": 3
        },
        {
          "race": "orc",
          "players": [
            {
              "toonName": "CalmarRobot",
              "battleTag": "CalmarRobot#221597",
              "avatarId": "p073",
              "accountCreationTime": 18446744071881645412
            }
          ],
          "region": "",
          "mmr": 4156,
          "gameMode": "",
          "rank": 31525,
          "wins": 58,
          "losses": 52,
          "draws": 0,
          "division": 3
        }
      ],
      "lastAccessTime": 1705961001
    }
  }
}