{
  "messageType": "UpdateLeaderboardData",
  "payload": {
    "message": {
      "region": "",
      "gameMode": "1v1",
      "race": "all",
      "seasonId": 3,
      "totalrows": 42949,
      "totalpages": 1718,
      "currentpage": 886,
      "hasError": false,
      "errorMessage": "",
      "rows": [
        {
          "race": "orc",
          "players": [
            {
              "toonName": "Oilberta",
              "battleTag": "Oilberta#1456",
              "avatarId": "",
              "accountCreationTime": 1353094542
            }
          ],
          "region": "",
          "mmr": 4514,
          "gameMode": "",
          "rank": 22126,
          "wins": 45,
          "losses": 49,
          "draws": 0,
          "division": 3
        },
        {
          "race": "night_elf",
          "players": [
            {
              "toonName": "TheSolution",
              "battleTag": "TheSolution#3303",
              "avatarId": "",
              "accountCreationTime": 18446744073318145557
            }
          ],
          "region": "",
          "mmr": 4514,
          "gameMode": "",
          "rank": 22127,
          "wins": 1,
          "losses": 5,
          "draws": 0,
          "division": 3
        },
        {
          "race": "human",
          "players": [
            {
              "toonName": "dnns92",
              "battleTag": "dnns92#2424",
              "avatarId": "p035",
              "accountCreationTime": 18446744073250610547
            }
          ],
          "region": "",
          "mmr": 4514,
          "gameMode": "",
          "rank": 22128,
          "wins": 2,
          "losses": 5,
          "draws": 0,
          "division": 3
        },
        {
          "race": "undead",
          "players": [
            {
              "toonName": "Jerome",
              "battleTag": "Jerome#3627",
              "avatarId": "",
              "accountCreationTime": 18446744072398673082
            }
          ],
          "region": "",
          "mmr": 4513,
          "gameMode": "",
          "rank": 22129,
          "wins": 5,
          "losses": 9,
          "draws": 0,
          "division": 3
        },
        {
          "race": "random",
          "players": [
            {
              "toonName": "大迪",
              "battleTag": "大迪#31528",
              "avatarId": "",
              "accountCreationTime": 18446744073182325443
            }
          ],
          "region": "",
          "mmr": 4513,
          "gameMode": "",
          "rank": 22130,
          "wins": 5,
          "losses": 9,
          "draws": 0,
          "division": 3
        },
        {
          "race": "night_elf",
          "players": [
            {
              "toonName": "grubby",
              "battleTag": "grubby#31173",
              "avatarId": "",
              "accountCreationTime": 18446744071700818646
            }
          ],
          "region": "",
          "mmr": 4513,
          "gameMode": "",
          "rank": 22131,
          "wins": 9,
          "losses": 12,
          "draws": 0,
          "division": 3
        },
        {
          "race": "orc",
          "players": [
            {
              "toonName": "Dits",
              "battleTag": "Dits#31676",
              "avatarId": "",
              "accountCreationTime": 18446744072647121870
            }
          ],
          "region": "",
          "mmr": 4513,
          "gameMode": "",
          "rank": 22132,
          "wins": 1,
          "losses": 5,
          "draws": 0,
          "division": 3
        },
        {
          "race": "night_elf",
          "players": [
            {
              "toonName": "江南王九",
              "battleTag": "江南王九#3781",
              "avatarId": "",
              "accountCreationTime": 18446744072972578138
            }
          ],
          "region": "",
          "mmr": 4513,
          "gameMode": "",
          "rank": 22133,
          "wins": 2,
          "losses": 4,
          "draws": 0,
          "division": 3
        },
        {
          "race": "random",
          "players": [
            {
              "toonName": "mrpietero",
              "battleTag": "mrpietero#2989",
              "avatarId": "p068",
              "accountCreationTime": 1900727076
            }
          ],
          "region": "",
          "mmr": 4513,
          "gameMode": "",
          "rank": 22134,
          "wins": 6,
          "losses": 10,
          "draws": 0,
          "division": 3
        },
        {
          "race": "orc",
          "players": [
            {
              "toonName": "DAMINIAN",
              "battleTag": "DAMINIAN#21920",
              "avatarId": "p034",
              "accountCreationTime": 260125562
            }
          ],
          "region": "",
          "mmr": 4513,
          "gameMode": "",
          "rank": 22135,
          "wins": 2,
          "losses": 5,
          "draws": 0,
          "division": 3
        },
        {
          "race": "human",
          "players": [
            {
              "toonName": "樂天盜賊",
              "battleTag": "樂天盜賊#315406",
              "avatarId": "p033",
              "accountCreationTime": 18446744072202284604
            }
          ],
          "region": "",
          "mmr": 4513,
          "gameMode": "",
          "rank": 22136,
          "wins": 1,
          "losses": 5,
          "draws": 0,
          "division": 3
        },
        {
          "race": "orc",
          "players": [
            {
              "toonName": "CFwoe",
              "battleTag": "CFwoe#1159",
              "avatarId": "",
              "accountCreationTime": 18446744073128775678
            }
          ],
          "region": "",
          "mmr": 4513,
          "gameMode": "",
          "rank": 22137,
          "wins": 8,
          "losses": 15,
          "draws": 0,
          "division": 3
        },
        {
          "race": "orc",
          "players": [
            {
              "toonName": "Wubi",
              "battleTag": "Wubi#21956",
              "avatarId": "p034",
              "accountCreationTime": 1109204333
            }
          ],
          "region": "",
          "mmr": 4513,
          "gameMode": "",
          "rank": 22138,
          "wins": 1,
          "losses": 5,
          "draws": 0,
          "division": 3
        },
        {
          "race": "random",
          "players": [
            {
              "toonName": "Endrys",
              "battleTag": "Endrys#2992",
              "avatarId": "p056",
              "accountCreationTime": 18446744071606735994
            }
          ],
          "region": "",
          "mmr": 4513,
          "gameMode": "",
          "rank": 22139,
          "wins": 15,
          "losses": 24,
          "draws": 0,
          "division": 3
        },
        {
          "race": "orc",
          "players": [
            {
              "toonName": "Vano888",
              "battleTag": "Vano888#21348",
              "avatarId": "p068",
              "accountCreationTime": 2017447131
            }
          ],
          "region": "",
          "mmr": 4513,
          "gameMode": "",
          "rank": 22140,
          "wins": 2,
          "losses": 8,
          "draws": 0,
          "division": 3
        },
        {
          "race": "night_elf",
          "players": [
            {
              "toonName": "Zaychik",
              "battleTag": "Zaychik#1214",
              "avatarId": "",
              "accountCreationTime": 1872788249
            }
          ],
          "region": "",
          "mmr": 4513,
          "gameMode": "",
          "rank": 22141,
          "wins": 19,
          "losses": 20,
          "draws": 0,
          "division": 3
        },
        {
          "race": "orc",
          "players": [
            {
              "toonName": "LordMonkey",
              "battleTag": "LordMonkey#11461",
              "avatarId": "",
              "accountCreationTime": 1671795873
            }
          ],
          "region": "",
          "mmr": 4513,
          "gameMode": "",
          "rank": 22142,
          "wins": 2,
          "losses": 3,
          "draws": 0,
          "division": 3
        },
        {
          "race": "random",
          "players": [
            {
              "toonName": "dasupafreak",
              "battleTag": "dasupafreak#1183",
              "avatarId": "",
              "accountCreationTime": 1393083083
            }
          ],
          "region": "",
          "mmr": 4513,
          "gameMode": "",
          "rank": 22143,
          "wins": 3,
          "losses": 6,
          "draws": 0,
          "division": 3
        },
        {
          "race": "orc",
          "players": [
            {
              "toonName": "Cruxx",
              "battleTag": "Cruxx#2399",
              "avatarId": "p033",
              "accountCreationTime": 330815482
            }
          ],
          "region": "",
          "mmr": 4513,
          "gameMode": "",
          "rank": 22144,
          "wins": 2,
          "losses": 6,
          "draws": 0,
          "division": 3
        },
        {
          "race": "random",
          "players": [
            {
              "toonName": "saveRojava",
              "battleTag": "saveRojava#2924",
              "avatarId": "",
              "accountCreationTime": 1299816889
            }
          ],
          "region": "",
          "mmr": 4513,
          "gameMode": "",
          "rank": 22145,
          "wins": 1,
          "losses": 4,
          "draws": 0,
          "division": 3
        },
        {
          "race": "orc",
          "players": [
            {
              "toonName": "grievus247",
              "battleTag": "grievus247#2636",
              "avatarId": "p015",
              "accountCreationTime": 1397628291
            }
          ],
          "region": "",
          "mmr": 4513,
          "gameMode": "",
          "rank": 22146,
          "wins": 3,
          "losses": 9,
          "draws": 0,
          "division": 3
        },
        {
          "race": "orc",
          "players": [
            {
              "toonName": "Zakattack",
              "battleTag": "Zakattack#11974",
              "avatarId": "",
              "accountCreationTime": 18446744072242819923
            }
          ],
          "region": "",
          "mmr": 4513,
          "gameMode": "",
          "rank": 22147,
          "wins": 2,
          "losses": 6,
          "draws": 0,
          "division": 3
        },
        {
          "race": "undead",
          "players": [
            {
              "toonName": "DukeAdrian",
              "battleTag": "DukeAdrian#1523",
              "avatarId": "",
              "accountCreationTime": 18446744072270574398
            }
          ],
          "region": "",
          "mmr": 4513,
          "gameMode": "",
          "rank": 22148,
          "wins": 408,
          "losses": 329,
          "draws": 0,
          "division": 3
        },
        {
          "race": "undead",
          "players": [
            {
              "toonName": "Kleinriese",
              "battleTag": "Kleinriese#210484",
              "avatarId": "",
              "accountCreationTime": 518780433
            }
          ],
          "region": "",
          "mmr": 4513,
          "gameMode": "",
          "rank": 22149,
          "wins": 2,
          "losses": 4,
          "draws": 0,
          "division": 3
        },
        {
          "race": "human",
          "players": [
            {
              "toonName": "cdy",
              "battleTag": "cdy",
              "avatarId": "",
              "accountCreationTime": 18446744072804448110
            }
          ],
          "region": "",
          "mmr": 4513,
          "gameMode": "",
          "rank": 22150,
          "wins": 14,
          "losses": 25,
          "draws": 0,
          "division": 3
        }
      ],
      "lastAccessTime": 1705960612
    }
  }
}