{
  "messageType": "UpdateLeaderboardData",
  "payload": {
    "message": {
      "region": "",
      "gameMode": "2v2arranged",
      "race": "",
      "seasonId": 4,
      "totalrows": 892,
      "totalpages": 36,
      "currentpage": 5,
      "hasError": false,
      "errorMessage": "",
      "rows": [
        {
          "race": "night_elf",
          "players": [
            {
              "toonName": "MassOwn",
              "battleTag": "MassOwn#1977",
              "avatarId": "p037"
            },
            {
              "toonName": "Ichbinandrew",
              "battleTag": "Ichbinandrew#3297",
              "avatarId": ""
            }
          ],
          "region": "",
          "mmr": 5619,
          "gameMode": "",
          "rank": 101,
          "wins": 11,
          "losses": 2,
          "draws": 0,
          "division": 4
        },
        {
          "race": "undead",
          "players": [
            {
              "toonName": "WolfmaN",
              "battleTag": "WolfmaN#12854",
              "avatarId": "p003"
            },
            {
              "toonName": "Pr1m1t1ve",
              "battleTag": "Pr1m1t1ve#2381",
              "avatarId": ""
            }
          ],
          "region": "",
          "mmr": 5613,
          "gameMode": "",
          "rank": 102,
          "wins": 18,
          "losses": 3,
          "draws": 0,
          "division": 4
        },
        {
          "race": "undead",
          "players": [
            {
              "toonName": "orfey",
              "battleTag": "orfey",
              "avatarId": "p001"
            },
            {
              "toonName": "D3xTer",
              "battleTag": "D3xTer#21492",
              "avatarId": ""
            }
          ],
          "region": "",
          "mmr": 5608,
          "gameMode": "",
          "rank": 103,
          "wins": 6,
          "losses": 0,
          "draws": 0,
          "division": 4
        },
        {
          "race": "orc",
          "players": [
            {
              "toonName": "Abracadabra",
              "battleTag": "Abracadabra#11263",
              "avatarId": ""
            },
            {
              "toonName": "ltouKaiji",
              "battleTag": "ltouKaiji#1305",
              "avatarId": "p003"
            }
          ],
          "region": "",
          "mmr": 5606,
          "gameMode": "",
          "rank": 104,
          "wins": 9,
          "losses": 0,
          "draws": 0,
          "division": 4
        },
        {
          "race": "human",
          "players": [
            {
              "toonName": "herothe4got",
              "battleTag": "herothe4got#2208",
              "avatarId": "p088"
            },
            {
              "toonName": "SavoyTruffle",
              "battleTag": "SavoyTruffle#11694",
              "avatarId": "p022"
            }
          ],
          "region": "",
          "mmr": 5601,
          "gameMode": "",
          "rank": 105,
          "wins": 10,
          "losses": 1,
          "draws": 0,
          "division": 4
        },
        {
          "race": "night_elf",
          "players": [
            {
              "toonName": "Eclips",
              "battleTag": "Eclips#31339",
              "avatarId": ""
            },
            {
              "toonName": "수목원",
              "battleTag": "수목원#31639",
              "avatarId": ""
            }
          ],
          "region": "",
          "mmr": 5598,
          "gameMode": "",
          "rank": 106,
          "wins": 13,
          "losses": 2,
          "draws": 0,
          "division": 4
        },
        {
          "race": "orc",
          "players": [
            {
              "toonName": "지금치킨먹고싶다",
              "battleTag": "지금치킨먹고싶다#3782",
              "avatarId": ""
            },
            {
              "toonName": "아킬레우스",
              "battleTag": "아킬레우스#3215",
              "avatarId": ""
            }
          ],
          "region": "",
          "mmr": 5598,
          "gameMode": "",
          "rank": 107,
          "wins": 5,
          "losses": 0,
          "draws": 0,
          "division": 4
        },
        {
          "race": "orc",
          "players": [
            {
              "toonName": "HyYyBriS",
              "battleTag": "HyYyBriS#2549",
              "avatarId": "p118"
            },
            {
              "toonName": "HoWarD",
              "battleTag": "HoWarD#21143",
              "avatarId": "p056"
            }
          ],
          "region": "",
          "mmr": 5597,
          "gameMode": "",
          "rank": 108,
          "wins": 9,
          "losses": 0,
          "draws": 0,
          "division": 4
        },
        {
          "race": "night_elf",
          "players": [
            {
              "toonName": "한예유찬",
              "battleTag": "한예유찬#3391",
              "avatarId": ""
            },
            {
              "toonName": "OvO",
              "battleTag": "OvO#34991",
              "avatarId": ""
            }
          ],
          "region": "",
          "mmr": 5595,
          "gameMode": "",
          "rank": 109,
          "wins": 9,
          "losses": 0,
          "draws": 0,
          "division": 4
        },
        {
          "race": "human",
          "players": [
            {
              "toonName": "uAllGod",
              "battleTag": "uAllGod#3751",
              "avatarId": ""
            },
            {
              "toonName": "UuSsssss",
              "battleTag": "UuSsssss#3611",
              "avatarId": ""
            }
          ],
          "region": "",
          "mmr": 5590,
          "gameMode": "",
          "rank": 110,
          "wins": 12,
          "losses": 1,
          "draws": 0,
          "division": 4
        },
        {
          "race": "human",
          "players": [
            {
              "toonName": "Miroslav",
              "battleTag": "Miroslav#31610",
              "avatarId": ""
            },
            {
              "toonName": "CaraVigo",
              "battleTag": "CaraVigo#3799",
              "avatarId": ""
            }
          ],
          "region": "",
          "mmr": 5590,
          "gameMode": "",
          "rank": 111,
          "wins": 8,
          "losses": 0,
          "draws": 0,
          "division": 4
        },
        {
          "race": "night_elf",
          "players": [
            {
              "toonName": "슈퍼마로",
              "battleTag": "슈퍼마로#3681",
              "avatarId": "p040"
            },
            {
              "toonName": "FairyTale",
              "battleTag": "FairyTale#11746",
              "avatarId": "p020"
            }
          ],
          "region": "",
          "mmr": 5588,
          "gameMode": "",
          "rank": 112,
          "wins": 8,
          "losses": 1,
          "draws": 0,
          "division": 4
        },
        {
          "race": "random",
          "players": [
            {
              "toonName": "FaCe2FaCe",
              "battleTag": "FaCe2FaCe#21377",
              "avatarId": "p057"
            },
            {
              "toonName": "Psiqophat",
              "battleTag": "Psiqophat#2101",
              "avatarId": "p054"
            }
          ],
          "region": "",
          "mmr": 5586,
          "gameMode": "",
          "rank": 113,
          "wins": 49,
          "losses": 21,
          "draws": 0,
          "division": 4
        },
        {
          "race": "night_elf",
          "players": [
            {
              "toonName": "슈퍼그랑죠",
              "battleTag": "슈퍼그랑죠#31523",
              "avatarId": ""
            },
            {
              "toonName": "OvO",
              "battleTag": "OvO#34991",
              "avatarId": ""
            }
          ],
          "region": "",
          "mmr": 5584,
          "gameMode": "",
          "rank": 114,
          "wins": 8,
          "losses": 0,
          "draws": 0,
          "division": 4
        },
        {
          "race": "night_elf",
          "players": [
            {
              "toonName": "reusbvb",
              "battleTag": "reusbvb#21819",
              "avatarId": "p055"
            },
            {
              "toonName": "KR1me",
              "battleTag": "KR1me#21446",
              "avatarId": "p080"
            }
          ],
          "region": "",
          "mmr": 5581,
          "gameMode": "",
          "rank": 115,
          "wins": 14,
          "losses": 2,
          "draws": 0,
          "division": 4
        },
        {
          "race": "undead",
          "players": [
            {
              "toonName": "EbonGhost",
              "battleTag": "EbonGhost#15742",
              "avatarId": "p004"
            },
            {
              "toonName": "glowstick",
              "battleTag": "glowstick#11631",
              "avatarId": "p022"
            }
          ],
          "region": "",
          "mmr": 5581,
          "gameMode": "",
          "rank": 116,
          "wins": 16,
          "losses": 2,
          "draws": 0,
          "division": 4
        },
        {
          "race": "human",
          "players": [
            {
              "toonName": "lady",
              "battleTag": "lady#31294",
              "avatarId": ""
            },
            {
              "toonName": "ARON",
              "battleTag": "ARON#31412",
              "avatarId": ""
            }
          ],
          "region": "",
          "mmr": 5578,
          "gameMode": "",
          "rank": 117,
          "wins": 10,
          "losses": 2,
          "draws": 0,
          "division": 4
        },
        {
          "race": "random",
          "players": [
            {
              "toonName": "超级贝吉塔",
              "battleTag": "超级贝吉塔#31253",
              "avatarId": ""
            },
            {
              "toonName": "湾岸",
              "battleTag": "湾岸#3623",
              "avatarId": ""
            }
          ],
          "region": "",
          "mmr": 5575,
          "gameMode": "",
          "rank": 118,
          "wins": 22,
          "losses": 4,
          "draws": 0,
          "division": 4
        },
        {
          "race": "undead",
          "players": [
            {
              "toonName": "xingxing",
              "battleTag": "xingxing#11406",
              "avatarId": ""
            },
            {
              "toonName": "灰虫",
              "battleTag": "灰虫#3736",
              "avatarId": ""
            }
          ],
          "region": "",
          "mmr": 5575,
          "gameMode": "",
          "rank": 119,
          "wins": 11,
          "losses": 1,
          "draws": 0,
          "division": 4
        },
        {
          "race": "night_elf",
          "players": [
            {
              "toonName": "DoSa",
              "battleTag": "DoSa#31427",
              "avatarId": "p087"
            },
            {
              "toonName": "작은녹청전차",
              "battleTag": "작은녹청전차#31712",
              "avatarId": ""
            }
          ],
          "region": "",
          "mmr": 5573,
          "gameMode": "",
          "rank": 120,
          "wins": 7,
          "losses": 0,
          "draws": 0,
          "division": 4
        },
        {
          "race": "random",
          "players": [
            {
              "toonName": "Thaedalius",
              "battleTag": "Thaedalius#1362",
              "avatarId": "p098"
            },
            {
              "toonName": "ArminvB",
              "battleTag": "ArminvB#2981",
              "avatarId": "p052"
            }
          ],
          "region": "",
          "mmr": 5567,
          "gameMode": "",
          "rank": 121,
          "wins": 7,
          "losses": 0,
          "draws": 0,
          "division": 4
        },
        {
          "race": "orc",
          "players": [
            {
              "toonName": "mapio",
              "battleTag": "mapio#11236",
              "avatarId": ""
            },
            {
              "toonName": "sly5Z5",
              "battleTag": "sly5Z5#3347",
              "avatarId": ""
            }
          ],
          "region": "",
          "mmr": 5566,
          "gameMode": "",
          "rank": 122,
          "wins": 8,
          "losses": 1,
          "draws": 0,
          "division": 4
        },
        {
          "race": "undead",
          "players": [
            {
              "toonName": "hrDG",
              "battleTag": "hrDG#2188",
              "avatarId": "p053"
            },
            {
              "toonName": "Ego",
              "battleTag": "Ego#21619",
              "avatarId": "p022"
            }
          ],
          "region": "",
          "mmr": 5565,
          "gameMode": "",
          "rank": 123,
          "wins": 9,
          "losses": 0,
          "draws": 0,
          "division": 4
        },
        {
          "race": "human",
          "players": [
            {
              "toonName": "HoWarD",
              "battleTag": "HoWarD#21143",
              "avatarId": "p056"
            },
            {
              "toonName": "NfacSahne",
              "battleTag": "NfacSahne#2469",
              "avatarId": "p031"
            }
          ],
          "region": "",
          "mmr": 5565,
          "gameMode": "",
          "rank": 124,
          "wins": 20,
          "losses": 4,
          "draws": 0,
          "division": 4
        },
        {
          "race": "human",
          "players": [
            {
              "toonName": "Shady",
              "battleTag": "Shady#24451",
              "avatarId": "p071"
            },
            {
              "toonName": "BohunBGH",
              "battleTag": "BohunBGH#2985",
              "avatarId": "p030"
            }
          ],
          "region": "",
          "mmr": 5564,
          "gameMode": "",
          "rank": 125,
          "wins": 15,
          "losses": 5,
          "draws": 0,
          "division": 4
        }
      ],
      "lastAccessTime": 1707079807
    }
  }
}